kalkulyator/__init__.py
syntacticuz-0.2.dist-info/LICENSE.txt
syntacticuz-0.2.dist-info/METADATA
syntacticuz-0.2.dist-info/WHEEL
syntacticuz-0.2.dist-info/top_level.txt
syntacticuz-0.2.dist-info/RECORD
