Metadata-Version: 2.1
Name: syntacticuz
Version: 0.2
Summary: uzbek syntactic
Home-page: UNKNOWN
Author: Alisher Ismailov Shakirovich
Author-email: alisherismailov1991@gmail.com
License: MIT
Platform: UNKNOWN
Classifier: Programming Language :: Python :: 3
Classifier: License :: OSI Approved :: MIT License
Classifier: Operating System :: OS Independent
License-File: LICENSE.txt
